{
    "name": "land_intent",
    "slots": [{
            "name": "dt",
            "type": "dt"
        },
        {
            "name": "em",
            "type": "em"
        },
        {
            "name": "about",
            "type": "about"
        },
        {
            "name": "land_type",
            "type": "land_type",
            "samples": [
                "{land_type}"
            ]
        },
        {
            "name": "region",
            "type": "AMAZON.Country",
            "samples": [
                "country's name is {region}",
                "the name of the country is {region}",
                "name of country is {region}",
                "{region}"
            ]
        }
    ],
    "samples": [
        "{about} I want to know {em} in land",
        "{about} What is the {em} due to land types",
        "{about} The {em} in land {dt} {land_type} in {region}",
        "{about} What will be total {em}  in {region} {dt} {land_type}",
        "{about} Net {em} in {region} {dt} {land_type}",
        "{about} In {region} net {em} for {land_type}",
        "{about} Net removal due to {land_type} in {region}",
        "{about} Net {em} due to {land_type} in the {region}",
        "{about} Total {em} because of  {land_type} in {region}",
        "{about} {em} for {land_type} in {region}",
        "{about} Total {em} because of {land_type} in {region}",
        "{about} {em} due to {land_type} in {region}",
        "{about} {dt} {land_type} {em} in {region}",
        "{about} {em} {dt} {land_type} {em} in {region}",
        "{about} {em} {dt} {land_type}  in {region}",
        "{about} {land_type} {em} in {region}",
        "{about} {em} {dt} land in {region}",
        "{about} land {em} in {region}",
        "{about} land in {region}",
        "{dt} {land_type} {em} in {region}",
        "{em} {dt} {land_type} {em} in {region}",
        "{em} {dt} {land_type}  in {region}",
        "{land_type} {em} in {region}",
        "{em} {dt} land in {region}",
        "land {em} in {region}",
        "land in {region} ",
        "{about} {dt} {land_type} {em}",
        "{about} {em} {dt} {land_type} {em}",
        "{about} {em} {dt} {land_type} ",
        "{about} {land_type} {em}",
        "{about} {em} {dt} land",
        "{about} land {em}",
        "{about} land",
        "{dt} {land_type} {em}",
        "{em} {dt} {land_type} {em}",
        "{em} {dt} {land_type} ",
        "{land_type} {em}",
        "{em} {dt} land",
        "land {em}",
        "land",
        "I want to know {em} in land",
        "What is the {em} due to land types",
        "The {em} in land {dt} {land_type} in {region}",
        "What will be total {em}  in {region} {dt} {land_type}",
        "Net {em} in {region} {dt} {land_type}",
        "In {region} net {em} for {land_type}",
        "Net removal due to {land_type} in {region}",
        "Net {em} due to {land_type} in the {region}",
        "Total {em} because of  {land_type} in {region}",
        "{em} for {land_type} in {region}",
        "Total {em} because of {land_type} in {region}",
        "{em} due to {land_type} in {region}"
    ]
}